utils/__init__.py
utils/challenge_identification.py
utils/challenge_solver.py
utils/helpers.py
utils/user_agents.py
aiocfscraper-1.2.71.dist-info/METADATA
aiocfscraper-1.2.71.dist-info/WHEEL
aiocfscraper-1.2.71.dist-info/top_level.txt
aiocfscraper-1.2.71.dist-info/RECORD
